{
  "generated_at": "2026-06-18T14:23:30",
  "paper_start_date": "2014-09-17",
  "last_bar_date": "2026-06-18",
  "lifetime": {
    "years": 11.796703296703297,
    "total_return": 893.7093820040199,
    "cagr": 0.7791495143270024,
    "sharpe": 1.8597367084192293,
    "max_dd": -0.2816556138097178,
    "calmar": 2.7663198463829795
  },
  "reference_backtest": {
    "sharpe": 1.9,
    "cagr": 0.806,
    "maxdd": -0.282,
    "calmar": 2.86,
    "oos_sharpe": 1.52,
    "mc_sharpe_ci95": [
      1.77,
      2.01
    ],
    "live_expected_ci": [
      1.1,
      1.4
    ]
  },
  "windowed": {
    "30d": {
      "bars": 15,
      "stats": {
        "years": 0.08241758241758242,
        "total_return": -0.07152865492015481,
        "cagr": -0.5936272986721178,
        "sharpe": -5.143496170807977,
        "max_dd": -0.08953041324331867,
        "calmar": -6.630454134717378
      },
      "mc_bounds": {
        "n_bars": 15,
        "mean": 1.800361764197883,
        "std": 3.583754203798332,
        "p05": -4.540247228905257,
        "p25": -0.768023550580859,
        "p50": 2.3241655916500306,
        "p75": 4.463366416807846,
        "p95": 6.8355475659067535
      },
      "verdict": "\u26a0\ufe0f  BELOW p5 \u2014 under-performing backtest expected"
    },
    "90d": {
      "bars": 45,
      "stats": {
        "years": 0.24725274725274726,
        "total_return": -0.012860141977447004,
        "cagr": -0.051002834037005784,
        "sharpe": -0.0767976311402853,
        "max_dd": -0.14669001490971478,
        "calmar": -0.34769124584517336
      },
      "mc_bounds": {
        "n_bars": 45,
        "mean": 2.0034982078048476,
        "std": 1.9302193543242583,
        "p05": -1.3888063471160874,
        "p25": 0.7593576995341648,
        "p50": 2.2347677891956943,
        "p75": 3.3744029648019582,
        "p95": 4.9121693133194
      },
      "verdict": "\u2705 WITHIN expected range"
    },
    "180d": {
      "bars": 90,
      "stats": {
        "years": 0.4945054945054945,
        "total_return": -0.004318445693739514,
        "cagr": -0.008713582254241903,
        "sharpe": 0.05126564177095713,
        "max_dd": -0.1466900149097149,
        "calmar": -0.059401331846649266
      },
      "mc_bounds": {
        "n_bars": 90,
        "mean": 1.9665478015787916,
        "std": 1.3403116602387195,
        "p05": -0.32018649269350274,
        "p25": 1.115331001529995,
        "p50": 2.091730644059335,
        "p75": 2.8801584674179423,
        "p95": 3.9917817284576422
      },
      "verdict": "\u2705 WITHIN expected range"
    },
    "365d": {
      "bars": 182,
      "stats": {
        "years": 1.0,
        "total_return": -0.06009253736729081,
        "cagr": -0.06009253736729081,
        "sharpe": -0.3212346063874588,
        "max_dd": -0.14669001490971467,
        "calmar": -0.40965663139564606
      },
      "mc_bounds": {
        "n_bars": 182,
        "mean": 1.9408934319213376,
        "std": 0.8825606496507432,
        "p05": 0.5188640143119121,
        "p25": 1.334603430058018,
        "p50": 1.946500267131862,
        "p75": 2.5070835887629115,
        "p95": 3.4343669615536796
      },
      "verdict": "\u26a0\ufe0f  BELOW p5 \u2014 under-performing backtest expected"
    }
  }
}